liquidjango
