Metadata-Version: 1.0
Name: liquidjango
Version: 0.2.1
Summary: an interface to control a radio with liquidsoap
Home-page: https://bitbucket.org/adalovelace/liquidjango/overview
Author: Tatiana de la O
Author-email: acracia@cryptodrunks.net
License: gpl3
Platform: UNKNOWN
Classifier: Development Status :: 4 - Beta
Classifier: Framework :: Django
Classifier: Intended Audience :: Developers
Classifier: License :: OSI Approved :: GNU General Public License (GPL)
Classifier: Operating System :: OS Independent
Classifier: Programming Language :: Python
Classifier: Topic :: Internet :: WWW/HTTP
